{
  "c6_reviewed_reference_mutated": false,
  "c7_authorized": false,
  "full_transfer_claimed": false,
  "general_cell1_authority_claimed": false,
  "global_autonomy_claimed": false,
  "hidden_next_command": false,
  "latest_file_guessing": false,
  "mtime_selection": false,
  "new_domain_shift_executed": false,
  "prior_receipt_mutated": false,
  "runtime_effect": false,
  "runtime_patched": false,
  "runtime_wide_enforcement_claimed": false,
  "schema_version": "bounded_adoption_probe_boundary_review_v0",
  "source_mutated": false,
  "synthetic_protocol_only": true
}
