{
  "classes": [
    "CLEAN_BOUNDARY",
    "LOCAL_REPAIR_PRESSURE",
    "MISSING_MOVE_PRESSURE",
    "TAXONOMY_PRESSURE",
    "AUTHORITY_BOUNDARY",
    "EXTRACTION_BOUNDARY",
    "FRONTIER_BOUNDARY",
    "INVALID_RUN",
    "LOOP_PRESSURE"
  ],
  "law": [
    "halts are not automatically failures",
    "clean boundaries may be healthy",
    "authority boundaries may be expected",
    "legacy NO_APPLICABLE_MOVE must not impersonate completed proof or successful closure"
  ],
  "mapping": {
    "INVALID_REGIME": "INVALID_RUN",
    "INVALID_STATE": "INVALID_RUN",
    "NO_APPLICABLE_MOVE": "MISSING_MOVE_PRESSURE_LEGACY_ALIAS_ONLY",
    "REGIME_MISMATCH": "INVALID_RUN",
    "STEP_LIMIT_EXCEEDED": "LOOP_PRESSURE",
    "STOP_AUTHORITY_BOUNDARY": "AUTHORITY_BOUNDARY",
    "STOP_AUTHORITY_VIOLATION": "AUTHORITY_BOUNDARY",
    "STOP_DONE": "CLEAN_BOUNDARY",
    "STOP_FORBIDDEN_MOVE": "AUTHORITY_BOUNDARY",
    "STOP_FRONTIER": "FRONTIER_BOUNDARY",
    "STOP_HUMAN_REVIEW_REQUIRED": "AUTHORITY_BOUNDARY",
    "STOP_LAYER_COLLAPSE": "TAXONOMY_PRESSURE",
    "STOP_NEEDS_EXTRACTION": "EXTRACTION_BOUNDARY",
    "STOP_NEEDS_NEW_MOVE": "MISSING_MOVE_PRESSURE",
    "STOP_NEXT_MOVE_BOUNDARY": "CLEAN_BOUNDARY",
    "STOP_NO_APPLICABLE_MOVE": "MISSING_MOVE_PRESSURE",
    "STOP_PROJECTION_BUG": "LOCAL_REPAIR_PRESSURE",
    "STOP_PROPOSAL_REQUIRED": "AUTHORITY_BOUNDARY",
    "STOP_RECEIPT_MISMATCH": "LOCAL_REPAIR_PRESSURE",
    "STOP_TAXONOMY_GAP": "TAXONOMY_PRESSURE",
    "STOP_UNDERTYPED_OBJECT": "TAXONOMY_PRESSURE",
    "STOP_UNTYPED_UNIT": "TAXONOMY_PRESSURE",
    "STOP_VISIBLE_GOTCHA": "LOCAL_REPAIR_PRESSURE"
  },
  "schema_version": "stop_class_mapping_v0"
}
