{
  "case_id": "n9_one_sided_suspension",
  "compression_ratio": 37.0,
  "cycle_n": 37,
  "depth": 9,
  "family": "one_sided_suspension",
  "halt_reason": null,
  "matrix_cells": 414,
  "matrix_shape": [
    9,
    46
  ],
  "move_id": "duplicate_existing_column",
  "moves_reused": 36,
  "new_move_required": false,
  "rank_after": 8,
  "rank_before": 8,
  "receipt_path": "data/receipts/run_20260618_021815/n9_one_sided_suspension/cycle_0037.json",
  "registered_moves_total": 1,
  "run_id": "run_20260618_021815",
  "state_sig8_after": "033f5f6b",
  "state_sig8_before": "308a1ce3",
  "trajectory_signature": "b2fae4b7"
}