{
  "case_id": "n56_one_sided_suspension",
  "compression_ratio": 39.0,
  "cycle_n": 39,
  "depth": 56,
  "family": "one_sided_suspension",
  "halt_reason": null,
  "matrix_cells": 5320,
  "matrix_shape": [
    56,
    95
  ],
  "move_id": "duplicate_existing_column",
  "moves_reused": 38,
  "new_move_required": false,
  "rank_after": 55,
  "rank_before": 55,
  "receipt_path": "data/receipts/run_20260618_031231/n56_one_sided_suspension/cycle_0039.json",
  "registered_moves_total": 1,
  "run_id": "run_20260618_031231",
  "state_sig8_after": "0e9eb043",
  "state_sig8_before": "4135c219",
  "trajectory_signature": "f1223f8f"
}