{
  "a0_build_guards": {
    "authority_widened": false,
    "build_only_no_live_application": true,
    "builder_command_executed": false,
    "hidden_next_command": false,
    "latest_or_mtime_selection_used": false,
    "optimization_authorized": false,
    "prior_receipts_mutated": false,
    "repair_executed": false,
    "source_mutated": false,
    "strategic_discussion_as_authority": false,
    "taxonomy_delta_applied": false
  },
  "a0_build_summary": {
    "adapter_script_emitted": true,
    "build_result": "A0_RECEIPT_TO_BUILDER_TRANSITION_LAYER_BUILT",
    "builder_command_executed_count": 0,
    "classifier_table_emitted": true,
    "first_live_use_candidate": "APPLY_A0_TO_CURRENT_RECEIPT_CHAIN_FRONTIER_V0",
    "live_frontier_application_count": 0,
    "negative_control_count": 18,
    "negative_control_pass_count": 18,
    "probe_count": 7,
    "probe_pass_count": 7,
    "schemas_emitted": 6,
    "success_meaning": "A0 exists as a buildable transition layer from explicit receipt evidence to typed candidates or stop packets. No builder command executed."
  },
  "acceptance_gate_results": {
    "A0_TRANSITION_0_SOURCE_DESIGN_CONSUMED": true,
    "A0_TRANSITION_10_PROBE_RESULTS_EMITTED": true,
    "A0_TRANSITION_11_STOP_DONE_NULL_NEXT_DOES_NOT_EMIT_COMMAND": true,
    "A0_TRANSITION_12_FAILED_GATE_CLASSIFIES_REPAIR_CANDIDATE": true,
    "A0_TRANSITION_13_AMBIGUOUS_PRESSURE_CLASSIFIES_QUESTION_PACKET": true,
    "A0_TRANSITION_14_CAPABILITY_STOP_CLASSIFIES_MISSING_OBJECT_PROPOSAL": true,
    "A0_TRANSITION_15_CLOSE_FREEZE_CLASSIFIES_FINAL_ACCEPTANCE": true,
    "A0_TRANSITION_16_NO_COMMAND_EXECUTED": true,
    "A0_TRANSITION_17_NO_SOURCE_MUTATION": true,
    "A0_TRANSITION_18_NO_HIDDEN_NEXT_COMMAND": true,
    "A0_TRANSITION_1_HUMAN_DECISION_RECORDED": true,
    "A0_TRANSITION_2_OUTPUT_SCHEMA_EMITTED": true,
    "A0_TRANSITION_3_QUESTION_SET_EMITTED": true,
    "A0_TRANSITION_4_CLASSIFICATION_ENUM_EMITTED": true,
    "A0_TRANSITION_5_PRESSURE_ENUM_EMITTED": true,
    "A0_TRANSITION_6_COMMAND_CANDIDATE_SCHEMA_EMITTED": true,
    "A0_TRANSITION_7_MISSING_OBJECT_PROPOSAL_SCHEMA_EMITTED": true,
    "A0_TRANSITION_8_CLASSIFIER_TABLE_EMITTED": true,
    "A0_TRANSITION_9_PROBE_CASES_EMITTED": true
  },
  "aggregate_metrics": {
    "adapter_script_emitted_count": 1,
    "builder_command_executed_count": 0,
    "classification_enum_emitted_count": 1,
    "classifier_table_emitted_count": 1,
    "command_candidate_schema_emitted_count": 1,
    "existing_receipt_mutation_count": 0,
    "hidden_next_command_count": 0,
    "human_decision_recorded_count": 1,
    "live_frontier_application_count": 0,
    "missing_object_proposal_schema_emitted_count": 1,
    "negative_control_count": 18,
    "negative_control_pass_count": 18,
    "negative_control_results_emitted_count": 1,
    "output_schema_emitted_count": 1,
    "pressure_enum_emitted_count": 1,
    "probe_case_manifest_emitted_count": 1,
    "probe_count": 7,
    "probe_pass_count": 7,
    "probe_results_emitted_count": 1,
    "question_set_emitted_count": 1,
    "source_design_consumed_count": 1,
    "source_mutation_count": 0,
    "transition_layer_report_emitted_count": 1
  },
  "classification": null,
  "created_at": "2026-06-23T23:57:39.556557+00:00",
  "failures": [],
  "gate": "PASS",
  "human_decision": {
    "authorized": [
      "emit static schemas",
      "emit fixed interrogation question set",
      "emit closed classification enum",
      "emit pressure enum",
      "emit classifier table",
      "emit builder command candidate schema",
      "emit missing-object proposal schema",
      "emit probe case manifest",
      "run synthetic probe receipt classifications",
      "run non-writing negative controls",
      "emit adapter script",
      "stop with no next command goal"
    ],
    "decision": "BUILD_A0_RECEIPT_TO_BUILDER_TRANSITION_LAYER",
    "not_authorized": [
      "execute builder command",
      "execute repair",
      "mutate source artifacts",
      "mutate prior receipts",
      "invent next objective",
      "infer roadmap from vibes",
      "treat strategic discussion as authority",
      "treat STOP_DONE as automatic next command",
      "treat pressure as repair authorization",
      "treat scale stability as repair authorization",
      "treat missing field as value null without typed object proposal",
      "select live frontier by latest-file guessing",
      "select live frontier by mtime sorting",
      "apply A0 to current frontier in this unit"
    ],
    "scope": "Build A0 as the receipt-to-builder transition membrane. A0 consumes explicit receipt bundles, asks a fixed question set, classifies the lawful transition state, and emits only typed candidates or stop packets. It must never execute a builder command, infer a next objective from strategic discussion, use latest/mtime selection, widen authority, or treat STOP_DONE/null-next as a command license.",
    "source_design_object": "A0_RECEIPT_INTERROGATION_ADAPTER_V0"
  },
  "must_not_infer": [
    "do not infer next command",
    "do not infer live frontier",
    "do not infer builder command execution"
  ],
  "negative_controls": {
    "authority_widening_authorized_count": 0,
    "existing_receipt_mutation_count": 0,
    "hidden_next_command_count": 0,
    "latest_or_mtime_selection": 0,
    "optimization_authorized_count": 0,
    "pressure_counted_as_repair": 0,
    "proposal_counted_as_execution": 0,
    "repair_executed_count": 0,
    "source_mutation_count": 0,
    "taxonomy_delta_proposal_emitted_count": 0,
    "unbounded_or_no_cap_run_count": 0
  },
  "no_commit_reason": "build receipt intentionally has no commit yet because previous wrapper assertion failed before commit",
  "output_artifacts": {
    "adapter_script": "scripts/a0_receipt_to_builder_transition_layer_v0.py",
    "classification_enum": "data/a0_receipt_to_builder_transition_layer_v0/a0_classification_enum_v0.json",
    "classifier_table": "data/a0_receipt_to_builder_transition_layer_v0/a0_classifier_table_v0.json",
    "command_candidate_schema": "data/a0_receipt_to_builder_transition_layer_v0/a0_command_candidate_schema_v0.json",
    "implementation_receipt": "data/a0_receipt_to_builder_transition_layer_v0_receipts/067fcaed.json",
    "missing_object_proposal_schema": "data/a0_receipt_to_builder_transition_layer_v0/a0_missing_object_proposal_schema_v0.json",
    "negative_control_results": "data/a0_receipt_to_builder_transition_layer_v0/a0_negative_control_results.jsonl",
    "output_schema": "data/a0_receipt_to_builder_transition_layer_v0/a0_output_schema_v0.json",
    "pressure_enum": "data/a0_receipt_to_builder_transition_layer_v0/a0_pressure_enum_v0.json",
    "probe_case_manifest": "data/a0_receipt_to_builder_transition_layer_v0/a0_probe_case_manifest.json",
    "probe_results": "data/a0_receipt_to_builder_transition_layer_v0/a0_probe_results.jsonl",
    "question_set": "data/a0_receipt_to_builder_transition_layer_v0/a0_question_set_v0.json",
    "transition_layer_report": "data/a0_receipt_to_builder_transition_layer_v0/a0_transition_layer_report.json"
  },
  "receipt_id": "067fcaed",
  "receipt_path": "data/a0_receipt_to_builder_transition_layer_v0_receipts/067fcaed.json",
  "receipt_type": "A0_RECEIPT_TO_BUILDER_TRANSITION_LAYER_BUILD_RECEIPT",
  "remaining_pressure": [
    "NONE"
  ],
  "schema_version": "a0_receipt_to_builder_transition_layer_build_receipt_v0",
  "source_design_object": "A0_RECEIPT_INTERROGATION_ADAPTER_V0",
  "source_selection_rule": "explicit_receipt_path",
  "target_unit_id": "a0.receipt_to_builder_transition_layer.v0",
  "terminal": {
    "next_command_goal": null,
    "stop_code": "STOP_HUMAN_DECISION_REQUIRED",
    "type": "STOP"
  },
  "unit_id": "BUILD_A0_RECEIPT_TO_BUILDER_TRANSITION_LAYER_V0",
  "warnings": []
}
