{
  "case_id": "n82_one_sided_suspension",
  "compression_ratio": 79.0,
  "cycle_n": 79,
  "depth": 82,
  "family": "one_sided_suspension",
  "halt_reason": null,
  "matrix_cells": 13202,
  "matrix_shape": [
    82,
    161
  ],
  "move_id": "duplicate_existing_column",
  "moves_reused": 78,
  "new_move_required": false,
  "rank_after": 81,
  "rank_before": 81,
  "receipt_path": "data/receipts/run_20260618_022922/n82_one_sided_suspension/cycle_0079.json",
  "registered_moves_total": 1,
  "run_id": "run_20260618_022922",
  "state_sig8_after": "fc8f7bd8",
  "state_sig8_before": "09e2d125",
  "trajectory_signature": "9f18623f"
}