{
  "case_id": "n56_projection_quotient",
  "compression_ratio": 23.5,
  "cycle_n": 47,
  "depth": 56,
  "family": "projection_quotient",
  "halt_reason": null,
  "matrix_cells": 2640,
  "matrix_shape": [
    33,
    80
  ],
  "move_id": "append_zero_column",
  "moves_reused": 45,
  "new_move_required": false,
  "rank_after": 32,
  "rank_before": 32,
  "receipt_path": "data/receipts/run_20260618_021815/n56_projection_quotient/cycle_0047.json",
  "registered_moves_total": 2,
  "run_id": "run_20260618_021815",
  "state_sig8_after": "6627a74a",
  "state_sig8_before": "6656b842",
  "trajectory_signature": "fa7094e2"
}