{
  "case_id": "n47_projection_quotient",
  "compression_ratio": 14.0,
  "cycle_n": 28,
  "depth": 47,
  "family": "projection_quotient",
  "halt_reason": null,
  "matrix_cells": 2013,
  "matrix_shape": [
    33,
    61
  ],
  "move_id": "quotient_merge_last_row",
  "moves_reused": 26,
  "new_move_required": false,
  "rank_after": 32,
  "rank_before": 33,
  "receipt_path": "data/receipts/run_20260618_031231/n47_projection_quotient/cycle_0028.json",
  "registered_moves_total": 2,
  "run_id": "run_20260618_031231",
  "state_sig8_after": "b0c59e20",
  "state_sig8_before": "df378c82",
  "trajectory_signature": "b7512450"
}