{
  "case_id": "n55_projection_quotient",
  "compression_ratio": 27.0,
  "cycle_n": 54,
  "depth": 55,
  "family": "projection_quotient",
  "halt_reason": null,
  "matrix_cells": 2296,
  "matrix_shape": [
    28,
    82
  ],
  "move_id": "quotient_merge_last_row",
  "moves_reused": 52,
  "new_move_required": false,
  "rank_after": 27,
  "rank_before": 28,
  "receipt_path": "data/receipts/run_20260618_022922/n55_projection_quotient/cycle_0054.json",
  "registered_moves_total": 2,
  "run_id": "run_20260618_022922",
  "state_sig8_after": "3214434c",
  "state_sig8_before": "a123fbd0",
  "trajectory_signature": "59e7c021"
}