{
  "case_id": "n23_suspension_plus_repair",
  "final_rank": 22,
  "final_shape": [
    23,
    123
  ],
  "final_state_sig8": "a828fb6b",
  "halt_reason": "CYCLES_COMPLETE",
  "run_id": "run_20260618_031231",
  "trajectory": [
    "955f4a07",
    "e60911ae",
    "71ac2f5c",
    "64d19e99",
    "d85c7216",
    "da06b71a",
    "f9f7716d",
    "0b461503",
    "2bdf8205",
    "74639d17",
    "dc1efea7",
    "e3966673",
    "eb5adccc",
    "322ac9a0",
    "93a34900",
    "9f963609",
    "5006028a",
    "f6a5f128",
    "42a3fe05",
    "78501797",
    "1a2daade",
    "d117a19f",
    "eb05808f",
    "5bf2ae58",
    "3a278efe",
    "4112dd3c",
    "07083460",
    "e6799c66",
    "80c50436",
    "de4289bb",
    "ebe7dc37",
    "fc7be06e",
    "7047336d",
    "c8f5d179",
    "0732cdc5",
    "97ef492b",
    "6178b5f6",
    "c4df7512",
    "49ccfd6f",
    "7a6274a0",
    "acbf84e7",
    "c3441d71",
    "7c5b74c2",
    "14b42613",
    "4bd0a664",
    "25864c89",
    "f25d1b9f",
    "77e18db1",
    "f30ee234",
    "9e2de456",
    "e8bf7c63",
    "b1ceba2b",
    "64a2e70f",
    "d335c60d",
    "1f46a87a",
    "0ed99193",
    "96494f58",
    "62e7c3c6",
    "fc0af540",
    "62442818",
    "da4979ae",
    "d6e3fac1",
    "2713352e",
    "417cedae",
    "750da318",
    "5f2566be",
    "93c9769e",
    "dab0bd71",
    "b6e76590",
    "59e781cc",
    "f9ec5554",
    "1c021fd2",
    "ce0d38f3",
    "684b933d",
    "28406b4e",
    "c37836dd",
    "f5d7a050",
    "d38dc90e",
    "da397dd8",
    "232ded4b",
    "04833f46",
    "330d3645",
    "c8b5caa5",
    "c6f0ccf2",
    "326ed093",
    "67e2c5ba",
    "7ba7375e",
    "33af8f0f",
    "e6ff6c36",
    "b9962897",
    "475765c9",
    "8c3fa56d",
    "5fda54ac",
    "f089dc3a",
    "bbd5640c",
    "0e683e29",
    "5f13d10a",
    "39cdaf9f",
    "fe2c25ca",
    "a828fb6b"
  ],
  "trajectory_signature": "d738e033"
}