{
  "case_id": "n4_two_sided_suspension",
  "final_rank": 103,
  "final_shape": [
    104,
    104
  ],
  "final_state_sig8": "c014e9d5",
  "halt_reason": "CYCLES_COMPLETE",
  "run_id": "run_20260618_031231",
  "trajectory": [
    "e4854e15",
    "62e355e4",
    "808ea520",
    "9f7e4b57",
    "7771507a",
    "a78de502",
    "137f16fe",
    "c759c29b",
    "f7c88adc",
    "252078b1",
    "ae40a60a",
    "75096bb8",
    "a9b27b76",
    "e926c471",
    "f97e31f1",
    "b932199c",
    "a70157a0",
    "e242bd35",
    "5cdb1865",
    "c3f406f6",
    "e2f9d307",
    "dc83cd76",
    "ba384be0",
    "cf5c238a",
    "5e3f8440",
    "67ba6350",
    "52d0b54d",
    "a54cf958",
    "125ecbde",
    "207bd98f",
    "de2e2bc4",
    "37882fd3",
    "90cffb75",
    "6139af11",
    "9568ed26",
    "6d631830",
    "44f20da1",
    "0ce83bf6",
    "2b687c50",
    "8dfbb1ce",
    "f95bbd50",
    "8057bf0a",
    "5c26a543",
    "74845657",
    "a325add3",
    "1f005a04",
    "c32d048a",
    "af93530e",
    "afb30aac",
    "d0e7777b",
    "1ce2d2d6",
    "9c0e1e5c",
    "6fa4b7d0",
    "86895487",
    "12d87dc5",
    "3999dab7",
    "5dcff8e4",
    "12e2ccac",
    "10c31a70",
    "ea1900a5",
    "e392ff03",
    "e49abe90",
    "149a9cfa",
    "6f48a03b",
    "d1d9dfb5",
    "8d1334a0",
    "ff993cbb",
    "ec800617",
    "d32c2019",
    "8ee57792",
    "7a367471",
    "9a415a6d",
    "5f7c256c",
    "2f3803ae",
    "c432a06b",
    "3ce06962",
    "2c5218dc",
    "f191bb3a",
    "ea065986",
    "d4442a4f",
    "5cc7b7fa",
    "e2a22e5a",
    "1c56b1bc",
    "7cb312e9",
    "88409af0",
    "a4e06692",
    "cd674e21",
    "8abc424d",
    "38ee052a",
    "956ea5dd",
    "0ee0625d",
    "670de474",
    "51ab5a4a",
    "0632b6da",
    "f25d32b8",
    "4e4a4c5a",
    "e4bb0103",
    "7016bfa8",
    "d1f33283",
    "c014e9d5"
  ],
  "trajectory_signature": "9636f627"
}