{
  "case_id": "n76_projection_quotient",
  "final_rank": 25,
  "final_shape": [
    26,
    126
  ],
  "final_state_sig8": "bb5180a2",
  "halt_reason": "CYCLES_COMPLETE",
  "run_id": "run_20260618_031231",
  "trajectory": [
    "25f00819",
    "5c008706",
    "169297d6",
    "d7fb8a06",
    "277119aa",
    "9e061dfe",
    "503b59b4",
    "0fd13d02",
    "64b7fae5",
    "dd5ac284",
    "e58098e7",
    "1c80aaf0",
    "babbab08",
    "b3fbe702",
    "7fdd02cf",
    "58703d30",
    "921d8021",
    "fee354de",
    "b82faf7a",
    "a05e1fa1",
    "ad8a9bda",
    "e39eed29",
    "2baf07c9",
    "48fbbfb5",
    "7175b7d2",
    "96edb9f2",
    "aec25aa4",
    "0b1f8f4c",
    "69582977",
    "6ac20e9f",
    "acd09c25",
    "66b87879",
    "3d0a9c36",
    "f5c0de50",
    "a7fe399f",
    "423f9e7e",
    "9090cfcc",
    "b89878c0",
    "7245141a",
    "3d295b1c",
    "3ddd06be",
    "e752bab3",
    "36737e7b",
    "72bd5015",
    "7cf0c53d",
    "e57be467",
    "147b79b1",
    "e463125d",
    "68c99215",
    "5a20f2cd",
    "fa7cb3ab",
    "2f9635a0",
    "9e78978b",
    "0f3fe65b",
    "cf196ff6",
    "ce63bd59",
    "b55985b2",
    "152d6741",
    "5088ef23",
    "082212e9",
    "e5137a3d",
    "739e826f",
    "619579b6",
    "414aa644",
    "2fd634ae",
    "ad927172",
    "3aad47c4",
    "7ea66b12",
    "21901e3a",
    "a967a253",
    "343721b5",
    "ef9345f7",
    "03e3e3c5",
    "2b54f5ec",
    "f1c9ddcc",
    "e7133b73",
    "cf0353a4",
    "6a0d43d7",
    "54f7aaad",
    "2370f81a",
    "164314c9",
    "f0799073",
    "7ac47bbb",
    "81cf3e8d",
    "ea2b0fed",
    "355338a4",
    "dc695b30",
    "9457e7ae",
    "f1ab3186",
    "bf63b133",
    "99ae79c0",
    "5e2ee25c",
    "673e25c7",
    "4b1e3ff0",
    "1cd81421",
    "2a4803d8",
    "1d66a6d9",
    "c19a4e0d",
    "7bd96c7e",
    "bb5180a2"
  ],
  "trajectory_signature": "c74f4811"
}