{
  "case_id": "n82_projection_quotient",
  "final_rank": 31,
  "final_shape": [
    32,
    132
  ],
  "final_state_sig8": "bf053288",
  "halt_reason": "CYCLES_COMPLETE",
  "run_id": "run_20260618_031231",
  "trajectory": [
    "1998341b",
    "854296e0",
    "b1d1b39f",
    "faa9acbe",
    "253e2a14",
    "d8df117e",
    "a69833d7",
    "eb39595e",
    "77979258",
    "db018df0",
    "f81c8638",
    "56a3ede8",
    "162a199e",
    "b6278a7a",
    "4100b258",
    "bfa11c07",
    "b9632755",
    "55c17070",
    "fee9b60d",
    "fb775342",
    "3d30229a",
    "c12d9ea3",
    "87d16455",
    "4750e4e0",
    "c728797a",
    "fc21c8a2",
    "518f5747",
    "8d823259",
    "511e522a",
    "b186a406",
    "e7058fda",
    "22cd7487",
    "a8eee08c",
    "51f5ab23",
    "c3169ee5",
    "7ab75f43",
    "5e85e4b1",
    "f2cee4ed",
    "1a780a0d",
    "a946ea75",
    "eaa68a11",
    "fe3c96b3",
    "f07d6485",
    "385dc0d5",
    "7e632737",
    "0754ff5a",
    "c2ae933f",
    "f7dc0923",
    "aeaa8776",
    "09e03450",
    "2fd15407",
    "f08d5d11",
    "b313fa95",
    "525107af",
    "af4b8330",
    "463252c8",
    "087c9ca2",
    "9f2a86bf",
    "34325c27",
    "909fcb10",
    "04ce3744",
    "291407da",
    "de7e9ad1",
    "6fbb9419",
    "9d6a2c61",
    "b0827aa2",
    "8d409ed3",
    "7c7c5c55",
    "3ffc2a09",
    "80970591",
    "b9fb08e3",
    "f8b186d7",
    "8402a3d6",
    "7fed320a",
    "5039cad9",
    "0ececd07",
    "c64abde3",
    "947172a8",
    "3f378629",
    "e633feaf",
    "d676f924",
    "ec40713e",
    "815f5b89",
    "2bb0e578",
    "20607707",
    "e5f4e769",
    "e7b59f9f",
    "6332828f",
    "5a82d16b",
    "c20d4aa1",
    "bc328bab",
    "9b3da42d",
    "f9aefc9e",
    "2015ab73",
    "fb3e918c",
    "f8550498",
    "0f222d71",
    "97433a3c",
    "3cd49656",
    "bf053288"
  ],
  "trajectory_signature": "12375c0a"
}