{
  "case_id": "n70_projection_quotient",
  "compression_ratio": 24.0,
  "cycle_n": 48,
  "depth": 70,
  "family": "projection_quotient",
  "halt_reason": null,
  "matrix_cells": 4324,
  "matrix_shape": [
    46,
    94
  ],
  "move_id": "quotient_merge_last_row",
  "moves_reused": 46,
  "new_move_required": false,
  "rank_after": 45,
  "rank_before": 46,
  "receipt_path": "data/receipts/run_20260618_031231/n70_projection_quotient/cycle_0048.json",
  "registered_moves_total": 2,
  "run_id": "run_20260618_031231",
  "state_sig8_after": "e6a9dad0",
  "state_sig8_before": "addf5c32",
  "trajectory_signature": "494c3cd0"
}