{
  "case_id": "n22_two_sided_suspension",
  "compression_ratio": 7.0,
  "cycle_n": 7,
  "depth": 22,
  "family": "two_sided_suspension",
  "halt_reason": null,
  "matrix_cells": 841,
  "matrix_shape": [
    29,
    29
  ],
  "move_id": "add_row_and_link_column",
  "moves_reused": 6,
  "new_move_required": false,
  "rank_after": 28,
  "rank_before": 27,
  "receipt_path": "data/receipts/run_20260618_031231/n22_two_sided_suspension/cycle_0007.json",
  "registered_moves_total": 1,
  "run_id": "run_20260618_031231",
  "state_sig8_after": "d5e41464",
  "state_sig8_before": "330674d5",
  "trajectory_signature": "13fe0a6e"
}