{
  "case_id": "n37_two_sided_suspension",
  "compression_ratio": 87.0,
  "cycle_n": 87,
  "depth": 37,
  "family": "two_sided_suspension",
  "halt_reason": null,
  "matrix_cells": 15376,
  "matrix_shape": [
    124,
    124
  ],
  "move_id": "add_row_and_link_column",
  "moves_reused": 86,
  "new_move_required": false,
  "rank_after": 123,
  "rank_before": 122,
  "receipt_path": "data/receipts/run_20260618_031231/n37_two_sided_suspension/cycle_0087.json",
  "registered_moves_total": 1,
  "run_id": "run_20260618_031231",
  "state_sig8_after": "4daeea2a",
  "state_sig8_before": "0bfac1c4",
  "trajectory_signature": "daa3007e"
}