{
  "case_id": "n79_one_sided_suspension",
  "compression_ratio": 69.0,
  "cycle_n": 69,
  "depth": 79,
  "family": "one_sided_suspension",
  "halt_reason": null,
  "matrix_cells": 11692,
  "matrix_shape": [
    79,
    148
  ],
  "move_id": "duplicate_existing_column",
  "moves_reused": 68,
  "new_move_required": false,
  "rank_after": 78,
  "rank_before": 78,
  "receipt_path": "data/receipts/run_20260618_022922/n79_one_sided_suspension/cycle_0069.json",
  "registered_moves_total": 1,
  "run_id": "run_20260618_022922",
  "state_sig8_after": "f12fd9d7",
  "state_sig8_before": "9d1022d0",
  "trajectory_signature": "3007dd9e"
}