{
  "case_id": "n78_suspension_plus_repair",
  "compression_ratio": 80.0,
  "cycle_n": 80,
  "depth": 78,
  "family": "suspension_plus_repair",
  "halt_reason": null,
  "matrix_cells": 12324,
  "matrix_shape": [
    78,
    158
  ],
  "move_id": "xor_repair_column",
  "moves_reused": 79,
  "new_move_required": false,
  "rank_after": 77,
  "rank_before": 77,
  "receipt_path": "data/receipts/run_20260618_031231/n78_suspension_plus_repair/cycle_0080.json",
  "registered_moves_total": 1,
  "run_id": "run_20260618_031231",
  "state_sig8_after": "b5a4082b",
  "state_sig8_before": "b557bcd1",
  "trajectory_signature": "d23e0462"
}