{
  "available_evidence": [
    "selected pressure group class",
    "selected pressure subtype",
    "selected halt reason",
    "selected row count",
    "selection authority packet",
    "queue reconciliation provenance"
  ],
  "inspection_surface_id": "f493ed11",
  "materialized_from": "data/r1000_pressure_group_selection_from_reconciled_queue_v0/r1000_selected_pressure_group_from_reconciled_queue.json",
  "row_count": 19,
  "row_payload_inspected": false,
  "row_payload_materialized": false,
  "schema_version": "r1000_selected_pressure_group_inspection_surface_v0",
  "selected_group": {
    "halt_reason": "STOP_DONE",
    "parent_pressure_class": "BURDEN_PRESSURE",
    "pressure_subtype": "receipt_size_burden",
    "row_count": 19
  },
  "selected_pressure_group_id": "b9a7575a",
  "source_selection_receipt_id": "7c561212",
  "surface_status": "SELECTED_GROUP_METADATA_SURFACE_MATERIALIZED",
  "unavailable_evidence": [
    "individual selected-group row payloads",
    "per-row receipt-size measurements",
    "post-selection R1000 behavior"
  ]
}
