{
  "case_id": "n42_suspension_plus_repair",
  "final_rank": 41,
  "final_shape": [
    42,
    142
  ],
  "final_state_sig8": "f24665bc",
  "halt_reason": "CYCLES_COMPLETE",
  "run_id": "run_20260618_022922",
  "trajectory": [
    "76de58c5",
    "7412cde9",
    "5a4bb6e3",
    "ab6d9d6c",
    "53c89398",
    "064fe02b",
    "cc0dc672",
    "be78303d",
    "835adf33",
    "53d35902",
    "dcb525f4",
    "d2bab195",
    "53663744",
    "5a9878a4",
    "76649b6b",
    "e735e3da",
    "e2eb39d1",
    "255842d5",
    "cd6a5f23",
    "36d33990",
    "6e989486",
    "6214ad04",
    "ca2b9efe",
    "f92fc52e",
    "889b67cd",
    "5abd8a3a",
    "821ce31f",
    "d8444bf2",
    "b33d07ba",
    "61c753fe",
    "4c19f61b",
    "2a9bbfa9",
    "600b6885",
    "e47609f1",
    "2a61c615",
    "99cebe4b",
    "ff0a1ca3",
    "4092bbc6",
    "268624ff",
    "24c5269e",
    "355d22cd",
    "5d103bf7",
    "e39cc2ef",
    "a4a22bb2",
    "fc491933",
    "25529709",
    "c6af8111",
    "2231b364",
    "d01d33b1",
    "2366e629",
    "d970e0d8",
    "6299891c",
    "95d6acbc",
    "23026f14",
    "4a32223f",
    "f55da492",
    "ae53f06f",
    "3b749fe5",
    "c114da72",
    "cc4879e9",
    "0bfae0e0",
    "b01c9e0e",
    "d2928344",
    "2ca5219a",
    "c0d9515e",
    "5a607357",
    "0149332e",
    "52f9adb8",
    "8d983b82",
    "78126547",
    "756f3e72",
    "ccae7d85",
    "a8b508fa",
    "63d51810",
    "d914b813",
    "8f618f8e",
    "fa7ee236",
    "f548656a",
    "a03e53bc",
    "c21f5cf5",
    "8df1c98b",
    "d90b427d",
    "c7f32bfd",
    "c562c3eb",
    "7958a744",
    "fc81d93f",
    "57451206",
    "3a7182c3",
    "542866b6",
    "99ad3d0b",
    "3cb5caa8",
    "d686d9ad",
    "d2a4aaed",
    "7e9c0cf1",
    "15a4d993",
    "20a8f2f2",
    "f7901074",
    "eda0263d",
    "73bf8f5e",
    "f24665bc"
  ],
  "trajectory_signature": "2247e558"
}