{
  "case_id": "n50_projection_quotient",
  "final_rank": 1,
  "final_shape": [
    2,
    102
  ],
  "final_state_sig8": "8f17944b",
  "halt_reason": "CYCLES_COMPLETE",
  "run_id": "run_20260618_022922",
  "trajectory": [
    "3ed3cc3f",
    "35b42dd3",
    "8767c78c",
    "ece0e270",
    "6144b812",
    "e5036109",
    "795a0589",
    "1474305c",
    "2c53adb0",
    "51c6052f",
    "a91882ed",
    "94b2682a",
    "4f04f54e",
    "26277301",
    "3795d48a",
    "8bf88c5e",
    "4a6d8608",
    "0eaaa44f",
    "011120fe",
    "b12b6da5",
    "e1d386bb",
    "469bc4d9",
    "85e4cf5c",
    "4a0ecab3",
    "ed7d54da",
    "577650d0",
    "13b20fc7",
    "9434a872",
    "2eed92fb",
    "59bf8483",
    "776da0c6",
    "ec64f99a",
    "d18805a0",
    "4a61df76",
    "17d0e340",
    "4ba0ec6d",
    "ba01d1d2",
    "60030726",
    "6404175d",
    "0d803631",
    "becf3adc",
    "ddfb84c8",
    "0cc9c779",
    "abfabf13",
    "49118c24",
    "dbdd0005",
    "905ee6ea",
    "ce3b8d57",
    "f5bee773",
    "b41790d3",
    "70880057",
    "32570309",
    "1a1c28cc",
    "5ab65644",
    "04b06199",
    "cb98b06a",
    "c22b71b2",
    "65550d44",
    "00ebb31a",
    "8f331c4b",
    "71b01953",
    "156943ff",
    "40193094",
    "d9f81655",
    "27ead65c",
    "5bc51ae4",
    "e22c518a",
    "e0b5f964",
    "e6bfd3ad",
    "e5f5714e",
    "ae176c8a",
    "4fb24e67",
    "27ab9ebc",
    "d200e866",
    "e81a50ac",
    "68f2bebd",
    "86dc8d02",
    "597cff43",
    "639663cb",
    "9bff1a68",
    "29510439",
    "964742ae",
    "8b623bf3",
    "895a84c8",
    "e502d879",
    "1e5210c5",
    "fbca6eb5",
    "4de125c4",
    "7bb9ecdd",
    "9033297d",
    "3c38f49d",
    "e109ac77",
    "9862319e",
    "852400e6",
    "f6136abf",
    "d7851538",
    "9a69bab6",
    "98c435b8",
    "c2bb9922",
    "8f17944b"
  ],
  "trajectory_signature": "e788c2c3"
}