{
  "case_id": "n81_one_sided_suspension",
  "final_rank": 80,
  "final_shape": [
    81,
    181
  ],
  "final_state_sig8": "e2ab3bc8",
  "halt_reason": "CYCLES_COMPLETE",
  "run_id": "run_20260618_022922",
  "trajectory": [
    "47bbbc86",
    "07458bd8",
    "f546798c",
    "735c1f45",
    "e5bf3fe9",
    "7deafa9f",
    "4681cb9c",
    "bb4a1a1e",
    "ef1e1f95",
    "df53fc54",
    "a998341c",
    "df1a9a88",
    "7e4be932",
    "dd07ba49",
    "abff8428",
    "e00e8f71",
    "c5a4fedb",
    "0cdb3957",
    "919f71ab",
    "65bd562e",
    "6032e0d8",
    "6cb12be9",
    "6570dbe2",
    "63d8e791",
    "5946aff2",
    "fd04e27c",
    "58411549",
    "087f7bf5",
    "2e91c110",
    "9ff2378f",
    "8f64499d",
    "ac4d468a",
    "4d544ae2",
    "1da356d0",
    "ce32b52f",
    "8b11552b",
    "d055e77f",
    "f53d7e50",
    "37d54a1f",
    "1f9810f2",
    "c8167c3c",
    "368a239e",
    "dba4aaca",
    "a2a31be9",
    "a158dd3a",
    "5b5e416f",
    "4724e54f",
    "34339363",
    "11f8a364",
    "553fdedc",
    "e23cb30a",
    "eed654c5",
    "0ab45c23",
    "081e6a1d",
    "c0ea1b45",
    "e957ad82",
    "53ea89de",
    "ca5a9953",
    "7c80870a",
    "3ca34a6a",
    "9bcae54b",
    "aae5c94b",
    "efa47504",
    "6066aa02",
    "7f2fe501",
    "924c4652",
    "73b09505",
    "6beada24",
    "5e7e52a7",
    "0f14717c",
    "1dbaf4d5",
    "ba0518f2",
    "42cee168",
    "130b54f8",
    "90f1b057",
    "98ca1af9",
    "e5277021",
    "9373079f",
    "5283b0d0",
    "9c6bcb5c",
    "fc480ef0",
    "fedc42ef",
    "39aa155e",
    "4bc3fc7d",
    "9c000a37",
    "940a5774",
    "df37c002",
    "e1f1eebb",
    "6f38b04d",
    "b37ae392",
    "c4d5332f",
    "6f9f293d",
    "27b0de86",
    "54c5a809",
    "636e69a7",
    "9bbaa265",
    "1144db1d",
    "f043facd",
    "714b26d9",
    "e2ab3bc8"
  ],
  "trajectory_signature": "2916aedb"
}