{
  "case_id": "n46_two_sided_suspension",
  "compression_ratio": 79.0,
  "cycle_n": 79,
  "depth": 46,
  "family": "two_sided_suspension",
  "halt_reason": null,
  "matrix_cells": 15625,
  "matrix_shape": [
    125,
    125
  ],
  "move_id": "add_row_and_link_column",
  "moves_reused": 78,
  "new_move_required": false,
  "rank_after": 124,
  "rank_before": 123,
  "receipt_path": "data/receipts/run_20260618_031231/n46_two_sided_suspension/cycle_0079.json",
  "registered_moves_total": 1,
  "run_id": "run_20260618_031231",
  "state_sig8_after": "e845766e",
  "state_sig8_before": "4e81f48a",
  "trajectory_signature": "9ceb3a69"
}