{
  "case_id": "n52_projection_quotient",
  "compression_ratio": 16.0,
  "cycle_n": 32,
  "depth": 52,
  "family": "projection_quotient",
  "halt_reason": null,
  "matrix_cells": 2448,
  "matrix_shape": [
    36,
    68
  ],
  "move_id": "quotient_merge_last_row",
  "moves_reused": 30,
  "new_move_required": false,
  "rank_after": 35,
  "rank_before": 36,
  "receipt_path": "data/receipts/run_20260618_031231/n52_projection_quotient/cycle_0032.json",
  "registered_moves_total": 2,
  "run_id": "run_20260618_031231",
  "state_sig8_after": "2fa926a0",
  "state_sig8_before": "ef28c85c",
  "trajectory_signature": "9b46dfae"
}