{
  "adapter_unit_id": "proceed_adapter.v0",
  "authority_status": "PASS",
  "case_name": "PROCEED_ADVANCES_ONE_NAMED_UNIT",
  "created_at": "2026-06-22T12:25:31.012074+00:00",
  "failures": [],
  "fixture_id": "proceed_demo_proceed_advances_one_named_unit",
  "gate": "PASS",
  "hidden_continuation_authorized": false,
  "ledger_delta_present": true,
  "proposal_executed": false,
  "proposal_promoted": false,
  "readout_id": "5a4a1071",
  "readout_path": "data/proceed_adapter_v0_demo_readouts/5a4a1071.json",
  "receipt_delta_present": true,
  "receipt_id": "d960a1bd",
  "receipt_type": "PROCEED_ADAPTER_V0_DEMO_RECEIPT",
  "registry_written": false,
  "schema_version": "proceed_adapter_v0_demo_receipt_v0",
  "selected_unit": "proceed.unit.validate_current_surface.v0",
  "source_artifact_mutation": {
    "source_ledger_modified": false,
    "source_receipt_modified": false,
    "source_regime_modified": false,
    "source_runner_modified": false,
    "source_trace_modified": false
  },
  "taxonomy_delta_applied": false,
  "taxonomy_delta_promoted": false,
  "taxonomy_pressure_status": "NONE",
  "terminal_result": {
    "next_unit_id": "proceed.unit.execute_declared_runner_unit.v0",
    "stop_code": null,
    "type": "ADVANCE"
  },
  "trace_delta_present": true,
  "units_advanced_count": 1,
  "visible_gotcha_count": 0
}
