{
  "case_id": "n35_projection_quotient",
  "compression_ratio": 14.5,
  "cycle_n": 29,
  "depth": 35,
  "family": "projection_quotient",
  "halt_reason": null,
  "matrix_cells": 1050,
  "matrix_shape": [
    21,
    50
  ],
  "move_id": "append_zero_column",
  "moves_reused": 27,
  "new_move_required": false,
  "rank_after": 20,
  "rank_before": 20,
  "receipt_path": "data/receipts/run_20260618_031231/n35_projection_quotient/cycle_0029.json",
  "registered_moves_total": 2,
  "run_id": "run_20260618_031231",
  "state_sig8_after": "6a927409",
  "state_sig8_before": "f69a0060",
  "trajectory_signature": "d6af9117"
}