{
  "case_id": "n62_one_sided_suspension",
  "compression_ratio": 62.0,
  "cycle_n": 62,
  "depth": 62,
  "family": "one_sided_suspension",
  "halt_reason": null,
  "matrix_cells": 7688,
  "matrix_shape": [
    62,
    124
  ],
  "move_id": "duplicate_existing_column",
  "moves_reused": 61,
  "new_move_required": false,
  "rank_after": 61,
  "rank_before": 61,
  "receipt_path": "data/receipts/run_20260618_031231/n62_one_sided_suspension/cycle_0062.json",
  "registered_moves_total": 1,
  "run_id": "run_20260618_031231",
  "state_sig8_after": "d4edafd9",
  "state_sig8_before": "b2b0a728",
  "trajectory_signature": "170e5c81"
}