{
  "case_id": "n100_two_sided_suspension",
  "compression_ratio": 58.0,
  "cycle_n": 58,
  "depth": 100,
  "family": "two_sided_suspension",
  "halt_reason": null,
  "matrix_cells": 24964,
  "matrix_shape": [
    158,
    158
  ],
  "move_id": "add_row_and_link_column",
  "moves_reused": 57,
  "new_move_required": false,
  "rank_after": 157,
  "rank_before": 156,
  "receipt_path": "data/receipts/run_20260618_022922/n100_two_sided_suspension/cycle_0058.json",
  "registered_moves_total": 1,
  "run_id": "run_20260618_022922",
  "state_sig8_after": "c382a522",
  "state_sig8_before": "fc63e1c7",
  "trajectory_signature": "db04be0a"
}