{
  "application_authorized": false,
  "contract_status": "FIELD_POLICY_ENRICHMENT_CONTRACT_EMITTED_NOT_APPLIED",
  "field_policy_modified": false,
  "fields_under_review": [
    "direct_evidence_strength",
    "target_scope",
    "target_aspect",
    "comparison_grain",
    "inference_strength",
    "verification_gate_ref",
    "rollback_or_stop_boundary_ref"
  ],
  "required_field_policy_fields": [
    "field",
    "source_class",
    "required_source_object",
    "declared_source_role",
    "producer_unit_or_allowed_producer_units",
    "lineage_ref_or_source_packet_lineage_ref",
    "row_identity_keys"
  ],
  "schema_version": "typed_machine_readable_field_policy_enrichment_contract_v0"
}
