{
  "absence_reason_key_profile": {
    "current_label_space_ref": 25,
    "expected_label_space_ref": 25,
    "missing_label_identifier": 25,
    "taxonomy_context_ref": 25
  },
  "absence_reason_value_profile": {
    "current_label_space_ref": {
      "SOURCE_PAYLOAD_DOES_NOT_EMIT_FIELD": 25
    },
    "expected_label_space_ref": {
      "SOURCE_PAYLOAD_DOES_NOT_EMIT_FIELD": 25
    },
    "missing_label_identifier": {
      "SOURCE_PAYLOAD_DOES_NOT_EMIT_FIELD": 25
    },
    "taxonomy_context_ref": {
      "SOURCE_PAYLOAD_DOES_NOT_EMIT_FIELD": 25
    }
  },
  "all_absence_reasons_present": true,
  "all_nulls_have_source_payload_absence_reason": true,
  "all_required_field_keys_present": true,
  "all_required_field_values_present": false,
  "all_structural_refs_present": true,
  "any_required_field_value_present": false,
  "corrected_evidence_sufficiency_class": "EVIDENCE_SURFACE_PRESENT_CONTENT_ABSENT",
  "expected_field_row_count": 25,
  "field_row_count": 25,
  "field_surface_repair_validated": true,
  "key_presence_profile": {
    "current_label_space_ref": 25,
    "expected_label_space_ref": 25,
    "missing_label_identifier": 25,
    "taxonomy_context_ref": 25
  },
  "missing_label_values_guessed": false,
  "pressure_group_key_hash": "38c604a1",
  "review_only": true,
  "schema_version": "null_evidence_limit_input_rollup_v0",
  "source_comparison_gate_fix_receipt_id": "b554aace",
  "source_failed_rerun_receipt_id": "b113463f",
  "taxonomy_delta_evidence_present": false,
  "taxonomy_upgrade_evidence_present": false,
  "value_presence_profile": {
    "current_label_space_ref": 0,
    "expected_label_space_ref": 0,
    "missing_label_identifier": 0,
    "taxonomy_context_ref": 0
  }
}
