{
  "case_id": "n47_suspension_plus_repair",
  "compression_ratio": 46.0,
  "cycle_n": 46,
  "depth": 47,
  "family": "suspension_plus_repair",
  "halt_reason": null,
  "matrix_cells": 4371,
  "matrix_shape": [
    47,
    93
  ],
  "move_id": "xor_repair_column",
  "moves_reused": 45,
  "new_move_required": false,
  "rank_after": 46,
  "rank_before": 46,
  "receipt_path": "data/receipts/run_20260618_022922/n47_suspension_plus_repair/cycle_0046.json",
  "registered_moves_total": 1,
  "run_id": "run_20260618_022922",
  "state_sig8_after": "dbe68635",
  "state_sig8_before": "e088a3ba",
  "trajectory_signature": "5fdd4a95"
}