{
  "bad_counters_zero": true,
  "cell_id": "SCHEMA_VALIDATOR_CELL",
  "closure_result": "REVIEWED_REFERENCE_FROZEN",
  "live_runtime_routing_installed": false,
  "must_not_infer": [
    "Schema Validator is live runtime routing",
    "Runtime was patched",
    "Sidecar was designed",
    "C8 is authorized",
    "VALID means authorized",
    "VALID means admissible",
    "VALID means execute"
  ],
  "next_available_branch": "Runtime Observability Sidecar design, subject to separate decision",
  "next_command_goal": null,
  "profile_id": "runtime_schema_validator_reference_closure_528f24a0",
  "reference_status": "RUNTIME_SCHEMA_VALIDATOR_CELL_REVIEWED_REFERENCE_FROZEN",
  "runtime_patched": false,
  "schema_version": "runtime_schema_validator_reference_closure_profile_v0",
  "status": "TYPED_RUNTIME_SCHEMA_VALIDATOR_CELL_CLOSED_AS_REVIEWED_REFERENCE_DECISION_READY",
  "synthetic_demo_build_only": true
}
