{
  "case_id": "n22_projection_quotient",
  "compression_ratio": 14.5,
  "cycle_n": 29,
  "depth": 22,
  "family": "projection_quotient",
  "halt_reason": null,
  "matrix_cells": 296,
  "matrix_shape": [
    8,
    37
  ],
  "move_id": "append_zero_column",
  "moves_reused": 27,
  "new_move_required": false,
  "rank_after": 7,
  "rank_before": 7,
  "receipt_path": "data/receipts/run_20260618_031231/n22_projection_quotient/cycle_0029.json",
  "registered_moves_total": 2,
  "run_id": "run_20260618_031231",
  "state_sig8_after": "4d881476",
  "state_sig8_before": "b73f3e90",
  "trajectory_signature": "0fedc696"
}