{
  "case_id": "n97_one_sided_suspension",
  "compression_ratio": 29.0,
  "cycle_n": 29,
  "depth": 97,
  "family": "one_sided_suspension",
  "halt_reason": null,
  "matrix_cells": 12222,
  "matrix_shape": [
    97,
    126
  ],
  "move_id": "duplicate_existing_column",
  "moves_reused": 28,
  "new_move_required": false,
  "rank_after": 96,
  "rank_before": 96,
  "receipt_path": "data/receipts/run_20260618_022922/n97_one_sided_suspension/cycle_0029.json",
  "registered_moves_total": 1,
  "run_id": "run_20260618_022922",
  "state_sig8_after": "9ff10495",
  "state_sig8_before": "4fcc9dca",
  "trajectory_signature": "97441157"
}