{
  "contract_status": "UNDER_TYPED_ACCEPTANCE_CONTRACT_FROZEN",
  "record_schema": {
    "acceptance_candidate_id": "under_typed_acceptance_<sig8>",
    "acceptance_reason": null,
    "acceptance_scope": "LOCAL_REFERENCE_ONLY | C5_BLOCKING | PARKED",
    "c5_unblock_allowed": false,
    "human_or_validator_review_required": true,
    "schema_version": "o2_under_typed_acceptance_candidate_v0",
    "source_feedback_ref": null,
    "status": "CANDIDATE_ONLY"
  },
  "rule": "under-typed acceptance is candidate-only until explicitly reviewed; it does not unblock C5 by itself.",
  "schema_version": "o2_under_typed_acceptance_contract_v0"
}
