{
  "remaining_groups": [
    {
      "group_hash_candidates": {
        "candidate_key_hash": "09e3844d",
        "legacy_join_hash": "6a7910a8",
        "raw_tuple_hash": "dfce7bfd"
      },
      "group_key": {
        "halt_reason": "STOP_DONE",
        "parent_pressure_class": "BURDEN_PRESSURE",
        "pressure_subtype": "receipt_size_burden"
      },
      "queue_state": "OPEN_UNRESOLVED_PRESSURE_GROUP",
      "resolution": null,
      "resolution_source_receipt_id": "a121ff40",
      "row_count": 19,
      "sample_row_refs": [
        {
          "receipt_id": null,
          "row_index": 49,
          "work_item_id": "r1000_candidate_c_work_0049"
        },
        {
          "receipt_id": null,
          "row_index": 50,
          "work_item_id": "r1000_candidate_c_work_0050"
        },
        {
          "receipt_id": null,
          "row_index": 51,
          "work_item_id": "r1000_candidate_c_work_0051"
        },
        {
          "receipt_id": null,
          "row_index": 52,
          "work_item_id": "r1000_candidate_c_work_0052"
        },
        {
          "receipt_id": null,
          "row_index": 53,
          "work_item_id": "r1000_candidate_c_work_0053"
        }
      ],
      "semantic_tuple": [
        "BURDEN_PRESSURE",
        "receipt_size_burden",
        "STOP_DONE"
      ]
    },
    {
      "group_hash_candidates": {
        "candidate_key_hash": "9cd3a8d5",
        "legacy_join_hash": "b58122d4",
        "raw_tuple_hash": "b754d906"
      },
      "group_key": {
        "halt_reason": "STOP_NEEDS_EXTRACTION",
        "parent_pressure_class": "EXTRACTION_PRESSURE",
        "pressure_subtype": "evidence_missing"
      },
      "queue_state": "OPEN_UNRESOLVED_PRESSURE_GROUP",
      "resolution": null,
      "resolution_source_receipt_id": "a121ff40",
      "row_count": 16,
      "sample_row_refs": [
        {
          "receipt_id": null,
          "row_index": 68,
          "work_item_id": "r1000_candidate_c_work_0068"
        },
        {
          "receipt_id": null,
          "row_index": 69,
          "work_item_id": "r1000_candidate_c_work_0069"
        },
        {
          "receipt_id": null,
          "row_index": 70,
          "work_item_id": "r1000_candidate_c_work_0070"
        },
        {
          "receipt_id": null,
          "row_index": 71,
          "work_item_id": "r1000_candidate_c_work_0071"
        },
        {
          "receipt_id": null,
          "row_index": 72,
          "work_item_id": "r1000_candidate_c_work_0072"
        }
      ],
      "semantic_tuple": [
        "EXTRACTION_PRESSURE",
        "evidence_missing",
        "STOP_NEEDS_EXTRACTION"
      ]
    },
    {
      "group_hash_candidates": {
        "candidate_key_hash": "1ffcbd41",
        "legacy_join_hash": "0a0d7a53",
        "raw_tuple_hash": "d7b3a90a"
      },
      "group_key": {
        "halt_reason": "STOP_TAXONOMY_GAP",
        "parent_pressure_class": "BURDEN_PRESSURE",
        "pressure_subtype": "receipt_size_burden"
      },
      "queue_state": "OPEN_UNRESOLVED_PRESSURE_GROUP",
      "resolution": null,
      "resolution_source_receipt_id": "a121ff40",
      "row_count": 4,
      "sample_row_refs": [
        {
          "receipt_id": null,
          "row_index": 84,
          "work_item_id": "r1000_candidate_c_work_0084"
        },
        {
          "receipt_id": null,
          "row_index": 85,
          "work_item_id": "r1000_candidate_c_work_0085"
        },
        {
          "receipt_id": null,
          "row_index": 86,
          "work_item_id": "r1000_candidate_c_work_0086"
        },
        {
          "receipt_id": null,
          "row_index": 87,
          "work_item_id": "r1000_candidate_c_work_0087"
        }
      ],
      "semantic_tuple": [
        "BURDEN_PRESSURE",
        "receipt_size_burden",
        "STOP_TAXONOMY_GAP"
      ]
    }
  ],
  "remaining_open_group_count": 3,
  "remaining_open_row_count": 39,
  "schema_version": "r1000_remaining_pressure_groups_after_selected_group_inspection_v0"
}
