{
  "case_id": "n13_one_sided_suspension",
  "final_rank": 12,
  "final_shape": [
    13,
    53
  ],
  "final_state_sig8": "74ded7b8",
  "halt_reason": "CYCLES_COMPLETE",
  "run_id": "run_20260618_033735",
  "trajectory": [
    "5be5fd14",
    "0d8ff38e",
    "6c39c4df",
    "2ee389ba",
    "30e504e5",
    "7bef19f9",
    "085bc50e",
    "f20b68f9",
    "45bb9752",
    "db130041",
    "43c17158",
    "b61ea4be",
    "da997a31",
    "4ce9b96b",
    "c72a82d4",
    "daeb4a50",
    "f31faa28",
    "ae1a8e55",
    "f2ad791b",
    "0d2d97b8",
    "1cde4983",
    "065f75b5",
    "8891be39",
    "57f879ad",
    "54f62def",
    "5ca471c5",
    "8623a7a1",
    "ac0774b4",
    "a7e7b2c6",
    "a3643111",
    "54f072d6",
    "c21027a2",
    "14a4ac26",
    "d87fe078",
    "a559a0b3",
    "5b7c5b52",
    "ed4ff9c2",
    "09ab30db",
    "b6f73ef3",
    "74ded7b8"
  ],
  "trajectory_signature": "409ae7e1"
}