{
  "case_id": "n13_two_sided_suspension",
  "final_rank": 52,
  "final_shape": [
    53,
    53
  ],
  "final_state_sig8": "08edda11",
  "halt_reason": "CYCLES_COMPLETE",
  "run_id": "run_20260618_033735",
  "trajectory": [
    "de4870f4",
    "9d8fcfb8",
    "8dccdd68",
    "e39ae4b4",
    "04e38256",
    "7aeaaf0e",
    "22d8546c",
    "f2b521eb",
    "563685c6",
    "9e217cb0",
    "c7fa48e0",
    "66f81919",
    "b07ca665",
    "70cd8378",
    "18e69117",
    "33362eb6",
    "5075068e",
    "fbd90674",
    "026d8baa",
    "c2414c12",
    "9f1f8953",
    "792005f8",
    "7027c055",
    "c5d107d0",
    "10b4ef48",
    "f662905f",
    "98af3bad",
    "6f4c0698",
    "51b3e309",
    "2ed2d742",
    "24a71124",
    "00e83f7d",
    "2883cf6a",
    "a5edaa57",
    "6286ac88",
    "f07b7d8d",
    "ec01b2fe",
    "5387aec0",
    "6e87081c",
    "08edda11"
  ],
  "trajectory_signature": "d55dc526"
}