{
  "case_id": "n70_projection_quotient",
  "compression_ratio": 16.0,
  "cycle_n": 32,
  "depth": 70,
  "family": "projection_quotient",
  "halt_reason": null,
  "matrix_cells": 4644,
  "matrix_shape": [
    54,
    86
  ],
  "move_id": "quotient_merge_last_row",
  "moves_reused": 30,
  "new_move_required": false,
  "rank_after": 53,
  "rank_before": 54,
  "receipt_path": "data/receipts/run_20260618_022922/n70_projection_quotient/cycle_0032.json",
  "registered_moves_total": 2,
  "run_id": "run_20260618_022922",
  "state_sig8_after": "b98d632d",
  "state_sig8_before": "a0c9effa",
  "trajectory_signature": "692b0581"
}