{
  "case_id": "n61_suspension_plus_repair",
  "compression_ratio": 22.0,
  "cycle_n": 22,
  "depth": 61,
  "family": "suspension_plus_repair",
  "halt_reason": null,
  "matrix_cells": 5063,
  "matrix_shape": [
    61,
    83
  ],
  "move_id": "xor_repair_column",
  "moves_reused": 21,
  "new_move_required": false,
  "rank_after": 60,
  "rank_before": 60,
  "receipt_path": "data/receipts/run_20260618_022922/n61_suspension_plus_repair/cycle_0022.json",
  "registered_moves_total": 1,
  "run_id": "run_20260618_022922",
  "state_sig8_after": "a3756a28",
  "state_sig8_before": "d5a963a8",
  "trajectory_signature": "9daf1f97"
}