{
  "allowed_now": {
    "record_candidate_surface_set": true,
    "select_surface_for_review": true
  },
  "failures": [],
  "forbidden_counters": {
    "c8_rerun_count": 0,
    "cell1_build_count": 0,
    "frontier_solved_claim_count": 0,
    "general_cell1_authority_count": 0,
    "global_solution_claim_count": 0,
    "hidden_next_command_count": 0,
    "instrument_build_count": 0,
    "missing_instrument_proposal_count": 0,
    "probe_authorized_count": 0,
    "probe_executed_count": 0,
    "probe_prep_authorized_count": 0,
    "research_mode_opened_count": 0,
    "reusable_schema_authorized_count": 0,
    "selected_surface_accepted_count": 0,
    "source_artifact_mutation_count": 0,
    "surface_activated_count": 0,
    "verification_probe_count": 0
  },
  "gate": "PASS",
  "not_allowed_now": {
    "accept_selected_surface": true,
    "activate_selected_surface": true,
    "authorize_probe": true,
    "authorize_probe_prep": true,
    "authorize_reusable_schema": true,
    "build_cell1": true,
    "build_instrument": true,
    "claim_frontier_solved": true,
    "claim_global_solution": true,
    "create_missing_instrument_proposal": true,
    "execute_probe": true,
    "open_research_mode": true,
    "rerun_c8": true,
    "run_verification_probe": true
  },
  "schema_version": "c8_successor_surface_selection_boundary_audit_v0",
  "source_surface_selection_decision_id": "c8_successor_surface_selection_decision_4f336833",
  "source_surface_selection_packet_id": "c8_successor_surface_selection_packet_f7874bf3",
  "surface_selection_boundary_audit_id": "c8_successor_surface_selection_boundary_ee54442b",
  "warnings": []
}
