{
  "case_id": "n22_suspension_plus_repair",
  "compression_ratio": 81.0,
  "cycle_n": 81,
  "depth": 22,
  "family": "suspension_plus_repair",
  "halt_reason": null,
  "matrix_cells": 2266,
  "matrix_shape": [
    22,
    103
  ],
  "move_id": "xor_repair_column",
  "moves_reused": 80,
  "new_move_required": false,
  "rank_after": 21,
  "rank_before": 21,
  "receipt_path": "data/receipts/run_20260618_031231/n22_suspension_plus_repair/cycle_0081.json",
  "registered_moves_total": 1,
  "run_id": "run_20260618_031231",
  "state_sig8_after": "bc13a157",
  "state_sig8_before": "4524c4b7",
  "trajectory_signature": "c018472d"
}