{
  "case_id": "n11_two_sided_suspension",
  "compression_ratio": 2.0,
  "cycle_n": 2,
  "depth": 11,
  "family": "two_sided_suspension",
  "halt_reason": null,
  "matrix_cells": 169,
  "matrix_shape": [
    13,
    13
  ],
  "move_id": "add_row_and_link_column",
  "moves_reused": 1,
  "new_move_required": false,
  "rank_after": 12,
  "rank_before": 11,
  "receipt_path": "data/receipts/run_20260618_021815/n11_two_sided_suspension/cycle_0002.json",
  "registered_moves_total": 1,
  "run_id": "run_20260618_021815",
  "state_sig8_after": "2856a2b0",
  "state_sig8_before": "326e4a73",
  "trajectory_signature": "538c9d3f"
}