{
  "case_id": "n51_one_sided_suspension",
  "compression_ratio": 28.0,
  "cycle_n": 28,
  "depth": 51,
  "family": "one_sided_suspension",
  "halt_reason": null,
  "matrix_cells": 4029,
  "matrix_shape": [
    51,
    79
  ],
  "move_id": "duplicate_existing_column",
  "moves_reused": 27,
  "new_move_required": false,
  "rank_after": 50,
  "rank_before": 50,
  "receipt_path": "data/receipts/run_20260618_021815/n51_one_sided_suspension/cycle_0028.json",
  "registered_moves_total": 1,
  "run_id": "run_20260618_021815",
  "state_sig8_after": "3054a4a5",
  "state_sig8_before": "b0c8e991",
  "trajectory_signature": "c3f0c1b9"
}