{
  "case_id": "n34_projection_quotient",
  "compression_ratio": 10.5,
  "cycle_n": 21,
  "depth": 34,
  "family": "projection_quotient",
  "halt_reason": null,
  "matrix_cells": 1080,
  "matrix_shape": [
    24,
    45
  ],
  "move_id": "append_zero_column",
  "moves_reused": 19,
  "new_move_required": false,
  "rank_after": 23,
  "rank_before": 23,
  "receipt_path": "data/receipts/run_20260618_031231/n34_projection_quotient/cycle_0021.json",
  "registered_moves_total": 2,
  "run_id": "run_20260618_031231",
  "state_sig8_after": "36bd8e53",
  "state_sig8_before": "ba553c14",
  "trajectory_signature": "41a3fc01"
}