{
  "case_id": "n10_two_sided_suspension",
  "compression_ratio": 80.0,
  "cycle_n": 80,
  "depth": 10,
  "family": "two_sided_suspension",
  "halt_reason": null,
  "matrix_cells": 8100,
  "matrix_shape": [
    90,
    90
  ],
  "move_id": "add_row_and_link_column",
  "moves_reused": 79,
  "new_move_required": false,
  "rank_after": 89,
  "rank_before": 88,
  "receipt_path": "data/receipts/run_20260618_022922/n10_two_sided_suspension/cycle_0080.json",
  "registered_moves_total": 1,
  "run_id": "run_20260618_022922",
  "state_sig8_after": "8fc58563",
  "state_sig8_before": "165f9143",
  "trajectory_signature": "bfb5dd61"
}