{
  "active_object": "unit feedback records from static demo failed/stopped/blocked/under-typed units",
  "bad_counters_zero": true,
  "core_rule": "Failure feedback must say why, where, relative to what, what is blocked, and what smallest refinement would allow progress.",
  "feedback_readout_ref": "data/o2_unit_feedback_hardening_v0/unit_feedback_readout_v0.json",
  "feedback_rollup_ref": "data/o2_unit_feedback_hardening_v0/unit_feedback_rollup_v0.json",
  "must_not_infer": [
    "repair applied",
    "target selected",
    "missing capability accepted",
    "refinement candidate approved",
    "C5 opened",
    "failure counted as progress"
  ],
  "next_command_goal": null,
  "profile_id": "o2_feedback_f86d0d7c",
  "schema_version": "o2_unit_feedback_hardening_profile_v0",
  "status": "O2_WEAK_FEEDBACK_REMAINS"
}
