{
  "case_id": "n54_suspension_plus_repair",
  "compression_ratio": 96.0,
  "cycle_n": 96,
  "depth": 54,
  "family": "suspension_plus_repair",
  "halt_reason": null,
  "matrix_cells": 8100,
  "matrix_shape": [
    54,
    150
  ],
  "move_id": "xor_repair_column",
  "moves_reused": 95,
  "new_move_required": false,
  "rank_after": 53,
  "rank_before": 53,
  "receipt_path": "data/receipts/run_20260618_031231/n54_suspension_plus_repair/cycle_0096.json",
  "registered_moves_total": 1,
  "run_id": "run_20260618_031231",
  "state_sig8_after": "fdc4ac93",
  "state_sig8_before": "daa05dd9",
  "trajectory_signature": "ea95e846"
}